lcovparse/__init__.py
lcovparse-0.0.5.dist-info/LICENSE
lcovparse-0.0.5.dist-info/METADATA
lcovparse-0.0.5.dist-info/WHEEL
lcovparse-0.0.5.dist-info/top_level.txt
lcovparse-0.0.5.dist-info/zip-safe
lcovparse-0.0.5.dist-info/RECORD
