Metadata-Version: 2.1
Name: lcovparse
Version: 0.0.5
Summary: lcov to json
Home-page: http://github.com/eyal0/lcovparse
Author: @eyal0
Author-email: hello@codecov.io
License: http://www.apache.org/licenses/LICENSE-2.0
Keywords: coverage
Platform: UNKNOWN
Classifier: Development Status :: 4 - Beta
Classifier: Environment :: Plugins
Classifier: Intended Audience :: Developers
Classifier: License :: OSI Approved :: Apache Software License
Classifier: Topic :: Software Development :: Testing
